{"customer_id": "cust_0001", "account_id": "acct_0001", "first_name": "Alice", "last_name": "Smith", "email": "alice.smith@example.com", "phone_hash": "5551234567", "address": "123 Main St", "city": "San Francisco", "state": "CA", "zip_code": "94105", "country": "USA", "ssn_hash": "hash_001", "date_of_birth": "1990-01-01", "kyc_date": "2024-07-01", "risk_score": 0.15, "employment_status": "employed", "annual_income": 120000.0}
{"customer_id": "cust_0002", "account_id": "acct_0002", "first_name": "Bob", "last_name": "Jones", "email": "bob.jones@example.com", "phone_hash": "5552345678", "address": "456 Market St", "city": "New York", "state": "NY", "zip_code": "10001", "country": "USA", "ssn_hash": "hash_002", "date_of_birth": "1985-05-05", "kyc_date": "2024-07-02", "risk_score": 0.22, "employment_status": "self-employed", "annual_income": 90000.0}
